{"data":{"site":{"siteMetadata":{"title":"Edgar Pino's Blog","author":"Edgar Pino"}},"markdownRemark":{"id":"be114413-2044-5b33-9b82-67686e97cd56","excerpt":"Welcome to part one of Getting Started with Ecto. This post is part of a series to teach you how to use Ecto. I will go over how to setup…","html":"<p>Welcome to part one of Getting Started with Ecto. This post is part of a series to teach you how to use Ecto. I will go over how to setup Ecto, create migrations and schemas, along with simple and more complicated queries. By the end of the series, you will be able to comfortably use Ecto in your Elixir applications.</p>\n<h2>What is Ecto?</h2>","frontmatter":{"title":"Getting Started with Ecto: Part 1","date":"September 26, 2018"}}},"pageContext":{"slug":"/getting-started-with-ecto-part-1/","previous":{"fields":{"slug":"/custom-urls-in-gatsby-blog-posts/"},"frontmatter":{"title":"Custom URLs in Gatsby Blog Posts"}},"next":null}}